{
  "placeholders": [
    {
      "key": "異常單號",
      "cell": "C2"
    },
    {
      "key": "發生日期",
      "cell": "A4"
    },
    {
      "key": "發生單位",
      "cell": "B4"
    },
    {
      "key": "責任單位",
      "cell": "C4"
    },
    {
      "key": "客戶",
      "cell": "D4"
    },
    {
      "key": "零件名稱",
      "cell": "E4"
    },
    {
      "key": "系列別",
      "cell": "F4"
    },
    {
      "key": "異常狀況",
      "cell": "G4"
    },
    {
      "key": "訂單數量",
      "cell": "H4"
    },
    {
      "key": "單號",
      "cell": "I4"
    },
    {
      "key": "異常比例",
      "cell": "J4"
    },
    {
      "key": "判定",
      "cell": "K4"
    },
    {
      "key": "異常標註內容",
      "cell": "M4"
    },
    {
      "key": "人工成本(人)",
      "cell": "M32"
    },
    {
      "key": "人工成本(時)",
      "cell": "O32"
    },
    {
      "key": "行政成本(人)",
      "cell": "R32"
    },
    {
      "key": "行政成本(時)",
      "cell": "T32"
    },
    {
      "key": "所耗人力成本",
      "cell": "Y32"
    }
  ]
}
